datacenter_datasdk/__init__.py
datacenter_datasdk/jdbc_api.py
datacenter_datasdk/pg_data.py
datacenter_datasdk/pg_model.py
datacenter_datasdk/restful_api.py
datacenter_datasdk/settings.py
datacenter_datasdk/taos-jdbcdriver-2.0.32-dist.jar
datacenter_datasdk/verify.py
datacenter_datasdk-0.2.26.dist-info/LICENSE.txt
datacenter_datasdk-0.2.26.dist-info/METADATA
datacenter_datasdk-0.2.26.dist-info/WHEEL
datacenter_datasdk-0.2.26.dist-info/top_level.txt
datacenter_datasdk-0.2.26.dist-info/zip-safe
datacenter_datasdk-0.2.26.dist-info/RECORD
