Metadata-Version: 2.1
Name: datacenter-datasdk
Version: 0.2.26
Summary: datacenter_datasdk
Home-page: UNKNOWN
Author: Wang Sheng
Author-email: jayed008@163.com
License: MIT
Platform: UNKNOWN
Classifier: Intended Audience :: Developers
Classifier: License :: OSI Approved :: MIT License
Classifier: Operating System :: MacOS
Classifier: Operating System :: Microsoft
Classifier: Operating System :: POSIX
Classifier: Operating System :: Unix
Classifier: Topic :: Software Development :: Libraries :: Python Modules
Classifier: Programming Language :: Python :: 3.7
Classifier: Programming Language :: Python :: 3.8
License-File: LICENSE.txt
Requires-Dist: pandas (>=0.25.3)
Requires-Dist: numpy (>=1.18.4)
Requires-Dist: python-dateutil
Requires-Dist: psycopg2-binary (~=2.8.6)
Requires-Dist: requests (==2.26.0)
Requires-Dist: SQLAlchemy
Requires-Dist: ahttp (==1.1.1)
Requires-Dist: aiohttp (==3.8.0)
Requires-Dist: nest-asyncio (==1.5.1)
Requires-Dist: JayDeBeApi (==1.2.3)
